fairsd/__init__.py
fairsd/algorithms.py
fairsd/discretization.py
fairsd/qualitymeasures.py
fairsd/searchspace.py
fairsd/sgdescription.py
fairsd-0.1.0.dist-info/METADATA
fairsd-0.1.0.dist-info/WHEEL
fairsd-0.1.0.dist-info/licenses/LICENSE
fairsd-0.1.0.dist-info/RECORD
