Metadata-Version: 2.3
Name: fairsd
Version: 0.1.0
Summary: Fair Subgroup Discovery fork of the original FairSD by Maurizio Pulizzi
Project-URL: Homepage, https://github.com/adubowski/fairsd
Author-email: Adam Dubowski <adubowski98@gmail.com>
License-File: LICENSE
Classifier: License :: OSI Approved :: MIT License
Classifier: Operating System :: OS Independent
Classifier: Programming Language :: Python :: 3
Requires-Python: >=3.8
